genescape/__about__.py
genescape/__init__.py
genescape/gs_graph.py
genescape/gs_index.py
genescape/gs_olap.py
genescape/icons.py
genescape/main.py
genescape/resources.py
genescape/utils.py
genescape/data/arabidopsis.index.gz
genescape/data/config.toml
genescape/data/ecoli.index.gz
genescape/data/fly.index.gz
genescape/data/go-basic.obo.gz
genescape/data/goa_human.gaf.gz
genescape/data/human.index.gz
genescape/data/mouse.index.gz
genescape/data/rat.index.gz
genescape/data/test_enrichr.txt
genescape/data/test_genes.txt
genescape/data/test_goids.txt
genescape/data/test_gprofiler.csv
genescape/data/test_input.csv
genescape/data/test_input.json
genescape/data/worm.index.gz
genescape/data/yeast.index.gz
genescape/data/zebrafish.index.gz
genescape/data/css/genescape.css
genescape/data/js/genescape-old.js
genescape/data/js/genescape.js
genescape/data/js/viz-standalone.js
genescape/shiny/tree/README.md
genescape/shiny/tree/app.py
genescape/shiny/tree/requirements.txt
genescape/shiny/tree/rsconnect-python/tree.json
genescape/shiny/tree/static/README.txt
genescape-1.0.6.dist-info/METADATA
genescape-1.0.6.dist-info/WHEEL
genescape-1.0.6.dist-info/entry_points.txt
genescape-1.0.6.dist-info/licenses/LICENSE.txt
genescape-1.0.6.dist-info/RECORD
