Metadata-Version: 2.3
Name: genescape
Version: 1.0.6
Project-URL: Documentation, https://github.com/ialbert/genescape-central#readme
Project-URL: Issues, https://github.com/ialbert/genescape-central/issues
Project-URL: Source, https://github.com/ialbert/genescape-central
Author-email: Istvan Albert <istvan.albert@gmail.com>
License-Expression: MIT
License-File: LICENSE.txt
Classifier: Development Status :: 4 - Beta
Classifier: Programming Language :: Python
Classifier: Programming Language :: Python :: 3.9
Classifier: Programming Language :: Python :: 3.10
Classifier: Programming Language :: Python :: 3.11
Classifier: Programming Language :: Python :: 3.12
Classifier: Programming Language :: Python :: Implementation :: CPython
Classifier: Programming Language :: Python :: Implementation :: PyPy
Requires-Python: >=3.9
Requires-Dist: click
Requires-Dist: faicons
Requires-Dist: networkx
Requires-Dist: pandas
Requires-Dist: pydot
Requires-Dist: shiny
Requires-Dist: toml
